Metadata-Version: 1.0
Name: fdking-distributions
Version: 1.0
Summary: Binomial & Gaussian Distributions Library
Home-page: UNKNOWN
Author: Fred King
Author-email: UNKNOWN
License: UNKNOWN
Platform: UNKNOWN
